<?xml version="1.0" encoding="UTF-8"?><soapenv:Envelope xmlns:soapenv="http://schemas.xmlsoap.org/soap/envelope/" xmlns:xsd="http://www.w3.org/2001/XMLSchema" xmlns:xsi="http://www.w3.org/2001/XMLSchema-instance"><soapenv:Header><platformMsgs:documentInfo xmlns:platformMsgs="urn:messages_2019_1.platform.webservices.netsuite.com"><platformMsgs:nsId>WEBSERVICES_6994672_SB1_042120212133691342013064630_d8538af6</platformMsgs:nsId></platformMsgs:documentInfo></soapenv:Header><soapenv:Body><deleteResponse xmlns="urn:messages_2019_1.platform.webservices.netsuite.com"><writeResponse><platformCore:status isSuccess="true" xmlns:platformCore="urn:core_2019_1.platform.webservices.netsuite.com"/><baseRef internalId="2936" type="account" xsi:type="platformCore:RecordRef" xmlns:platformCore="urn:core_2019_1.platform.webservices.netsuite.com"/></writeResponse></deleteResponse></soapenv:Body></soapenv:Envelope>